{"vuz_10003404": {"vuz_name": "Ноябрьский институт нефти и газа (филиал) федерального государственного бюджетного образовательного учреждения высшего образования «Тюменский индустриальный университет»", "vuz_link": "inst.php?id=10003404", "region": "10909", "vuz_id": "10003404"}, "vuz_12012854": {"vuz_name": "Салехардский филиал негосударственного образовательного частного учреждения высшего образования \"Уральский институт коммерции и права\"", "vuz_link": "inst.php?id=12012854", "region": "10909", "vuz_id": "12012854"}, "vuz_10001210": {"vuz_name": "Филиал ФГБОУ ВО \"Удмуртский государственный университет\" в г. Губкинском", "vuz_link": "inst.php?id=10001210", "region": "10909", "vuz_id": "10001210"}}